{
  "project_info": {
    "project_id": "tshirtapp-f0b54",
    "project_number": "8867200093",
    "name": "tshirtapp"
  },
  "client": [
    {
      "client_info": {
        "mobilesdk_app_id": "1:8867200093:android:024e9330e131962d",
        "client_id": "android:com.smamine.tshirapp",
        "client_type": 1,
        "android_client_info": {
          "package_name": "com.smamine.tshirapp",
          "certificate_hash": []
        }
      },
      "oauth_client": [],
      "api_key": [],
      "services": {
        "analytics_service": {
          "status": 1
        },
        "cloud_messaging_service": {
          "status": 2,
          "apns_config": []
        },
        "appinvite_service": {
          "status": 1,
          "other_platform_oauth_client": []
        },
        "google_signin_service": {
          "status": 1
        },
        "ads_service": {
          "status": 1
        }
      }
    }
  ],
  "client_info": [],
  "ARTIFACT_VERSION": "1"
}